{
  "project_info": {
    "project_number": "27229176057",
    "project_id": "datkhamapplication",
    "storage_bucket": "datkhamapplication.appspot.com"
  },
  "client": [
    {
      "client_info": {
        "mobilesdk_app_id": "1:27229176057:android:7e2d41061b89f3349ca228",
        "android_client_info": {
          "package_name": "edu.poly.datkhamapplication"
        }
      },
      "oauth_client": [
        {
          "client_id": "27229176057-vlsgov80pcno3p5fjmrp31lnsqimao1t.apps.googleusercontent.com",
          "client_type": 3
        }
      ],
      "api_key": [
        {
          "current_key": "AIzaSyD4Lo5IDtDFkwDAmiyiChcUiWXlJiFBUlE"
        }
      ],
      "services": {
        "appinvite_service": {
          "other_platform_oauth_client": [
            {
              "client_id": "27229176057-vlsgov80pcno3p5fjmrp31lnsqimao1t.apps.googleusercontent.com",
              "client_type": 3
            }
          ]
        }
      }
    }
  ],
  "configuration_version": "1"
}